ma100/__init__.py
ma100-0.1.0.dist-info/LICENSE
ma100-0.1.0.dist-info/METADATA
ma100-0.1.0.dist-info/WHEEL
ma100-0.1.0.dist-info/top_level.txt
ma100-0.1.0.dist-info/RECORD
